{
	"label": "Weapons",
	"entries": {
		"Assault Rifle": {
			"name": "Assault Rifle",
			"description": "<p>A standard-issue assault rifle. </p>"
		},
		"Baseball Bat": {
			"name": "Baseball Bat",
			"description": "<p>A firmly weighted bat. A favourite weapon of the Baseball Furies. </p>"
		},
		"Big Knucks": {
			"name": "Big Knucks",
			"description": "<p>Cyberware weapon. You must have the appropriate cyberware installed. </p>"
		},
		"Bow": {
			"name": "Bow",
			"description": "<p>A revitalized bow that must be reloaded after every attack. </p>"
		},
		"Chainsaw": {
			"name": "Chainsaw",
			"description": "<p>A portable, refuelable saw that runs on CHOOH2. Lasts about 2-3 hours on one tank. </p>"
		},
		"Combat Knife": {
			"name": "Combat Knife",
			"description": "<p>A knife fit for the streets.</p>"
		},
		"Crossbow": {
			"name": "Crossbow",
			"description": "<p>A crossbow which must be reloaded after every attack. </p>"
		},
		"Crowbar": {
			"name": "Crowbar",
			"description": "<p>Useful as both a tool and a weapon. A rod of iron with split wedges on the ends. </p>"
		},
		"Cybersnake": {
			"name": "Cybersnake",
			"description": "<p>Cyberware weapon. You must have the appropriate cyberware installed. </p>"
		},
		"Excellent Assault Rifle": {
			"name": "Excellent Assault Rifle",
			"description": "<p>A standard-issue assault rifle. +1 to Attack.</p>"
		},
		"Excellent Baseball Bat": {
			"name": "Excellent Baseball Bat",
			"description": "<p>A firmly weighted bat. A favourite weapon of the Baseball Furies. +1 to Attack.</p>"
		},
		"Excellent Bow": {
			"name": "Excellent Bow",
			"description": "<p>A revitalized bow that must be reloaded after every attack. +1 to Attack.</p>"
		},
		"Excellent Chainsaw": {
			"name": "Excellent Chainsaw",
			"description": "<p>A portable, refuelable saw that runs on CHOOH2. Lasts about 2-3 hours on one tank.  +1 to Attack.</p>"
		},
		"Excellent Combat Knife": {
			"name": "Excellent Combat Knife",
			"description": "<p>A knife fit for the streets. +1 to Attack.</p>"
		},
		"Excellent Crossbow": {
			"name": "Excellent Crossbow",
			"description": "<p>A crossbow which must be reloaded after every attack. +1 to Attack.</p>"
		},
		"Excellent Crowbar": {
			"name": "Excellent Crowbar",
			"description": "<p>Useful as both a tool and a weapon. A rod of iron with split wedges on the ends.  +1 to Attack.</p>"
		},
		"Excellent Grenade Launcher": {
			"name": "Excellent Grenade Launcher",
			"description": "<p>A high-impact grenade launcher. You can use a variety of grenades with this. +1 to Attack.</p>"
		},
		"Excellent Heavy Pistol": {
			"name": "Excellent Heavy Pistol",
			"description": "<p>A concealable, heavy pistol. +1 to Attack.</p>"
		},
		"Excellent Heavy SMG": {
			"name": "Excellent Heavy SMG",
			"description": "<p>A heavy SMG. Due to its size it can't be concealed. +1 to Attack.</p>"
		},
		"Excellent Helicopter Blades": {
			"name": "Excellent Helicopter Blades",
			"description": "<p>Taken from a derelict aircraft, these blades are capable of slicing most things easily.  +1 to Attack.</p>"
		},
		"Excellent Lead Pipe": {
			"name": "Excellent Lead Pipe",
			"description": "<p>A hollow cylinder, typically made of metal or fiberglass. It may have conveyed fluids once.  +1 to Attack.</p>"
		},
		"Excellent Machete": {
			"name": "Excellent Machete",
			"description": "<p>A long-bladed knife with a variety of uses. Known to be a favourite to some gangs  of Night City.  +1 to Attack.</p>"
		},
		"Excellent Medium Pistol": {
			"name": "Excellent Medium Pistol",
			"description": "<p>A concealable, medium-sized pistol. +1 to Attack.</p>"
		},
		"Excellent Naginata": {
			"name": "Excellent Naginata",
			"description": "<p>A japanese wooden pole with a curved blade on one side. Favoured by Arasaka tactical teams for close engagements.  +1 to Attack.</p>"
		},
		"Excellent Rocket Launcher": {
			"name": "Excellent Rocket Launcher",
			"description": "<p>Bring out the big guns. This rocket launcher will do some damage. +1 to Attack.</p>"
		},
		"Excellent SMG": {
			"name": "Excellent SMG",
			"description": "<p>A concealable SMG. +1 to Attack.</p>"
		},
		"Excellent Shotgun": {
			"name": "Excellent Shotgun",
			"description": "<p>An all-purpose shotgun. +1 to Attack.</p>"
		},
		"Excellent Sledgehammer": {
			"name": "Excellent Sledgehammer",
			"description": "<p>A large mallet-like object with a flat metal head which distributes impacted force over a wide area.  +1 to Attack.</p>"
		},
		"Excellent Sniper Rifle": {
			"name": "Excellent Sniper Rifle",
			"description": "<p>A long-distance sniper rifle. Holds 4 bullets in a magazine. +1 to Attack.</p>"
		},
		"Excellent Spiked Bat": {
			"name": "Excellent Spiked Bat",
			"description": "<p>An advancement over a regular bat. A number of nails have been hammered through towards the tip.  +1 to Attack.</p>"
		},
		"Excellent Sword": {
			"name": "Excellent Sword",
			"description": "<p>A bladed, hilted weapon. Specifically designed for cutting or thrusting.  +1 to Attack.</p>"
		},
		"Excellent Tomahawk": {
			"name": "Excellent Tomahawk",
			"description": "<p>A light axe that can be thrown. +1 to Attack.</p>"
		},
		"Excellent Very Heavy Pistol": {
			"name": "Excellent Very Heavy Pistol",
			"description": "<p>A very heavy pistol. It can't be concealed. +1 to Attack.</p>"
		},
		"Grenade Launcher": {
			"name": "Grenade Launcher",
			"description": "<p>A high-impact grenade launcher. You can use a variety of grenades with this. </p>"
		},
		"Heavy Pistol": {
			"name": "Heavy Pistol",
			"description": "<p>A concealable, heavy pistol. </p>"
		},
		"Heavy SMG": {
			"name": "Heavy SMG",
			"description": "<p>A heavy SMG. Due to its size it can't be concealed. </p>"
		},
		"Helicopter Blades": {
			"name": "Helicopter Blades",
			"description": "<p>Taken from a derelict aircraft, these blades are capable of slicing most things easily. </p>"
		},
		"Lead Pipe": {
			"name": "Lead Pipe",
			"description": "<p>A hollow cylinder, typically made of metal or fiberglass. It may have conveyed fluids once. </p>"
		},
		"Machete": {
			"name": "Machete",
			"description": "<p>A long-bladed knife with a variety of uses. Known to be a favourite to some gangs of Night City. </p>"
		},
		"Martial Arts": {
			"name": "Martial Arts",
			"description": "<p>Throwing hands, does ignore half armor.</p>"
		},
		"Medium Pistol": {
			"name": "Medium Pistol",
			"description": "<p>A concealable, medium-sized pistol. </p>"
		},
		"Naginata": {
			"name": "Naginata",
			"description": "<p>A japanese wooden pole with a curved blade on one side. Favoured by Arasaka tactical teams for close engagements. </p>"
		},
		"Poor Assault Rifle": {
			"name": "Poor Assault Rifle",
			"description": "<p>A standard-issue assault rifle.  If you roll 1 on Attack (Crit fail) the gun jams and requires using an action to clear. </p>"
		},
		"Poor Baseball Bat": {
			"name": "Poor Baseball Bat",
			"description": "<p>A firmly weighted bat. A favourite weapon of the Baseball Furies.  If you roll 1 on Attack (Crit Fail) the weapon fails in some way and requires an action to be made usable again.</p>"
		},
		"Poor Bow": {
			"name": "Poor Bow",
			"description": "<p>A revitalized bow that must be reloaded after every attack.  If you roll 1 on Attack (Crit fail) the gun jams and requires using an action to clear. </p>"
		},
		"Poor Chainsaw": {
			"name": "Poor Chainsaw",
			"description": "<p>A portable, refuelable saw that runs on CHOOH2. Lasts about 2-3 hours on one tank.  If you roll 1 on Attack (Crit Fail) the weapon fails in some way and requires an action to be made usable again.</p>"
		},
		"Poor Combat Knife": {
			"name": "Poor Combat Knife",
			"description": "<p>A knife fit for the streets. If you roll 1 on Attack (Crit Fail) the weapon fails in some way and requires an action to be made usable again.</p>"
		},
		"Poor Crossbow": {
			"name": "Poor Crossbow",
			"description": "<p>A crossbow which must be reloaded after every attack.  If you roll 1 on Attack (Crit fail) the gun jams and requires using an action to clear. </p>"
		},
		"Poor Crowbar": {
			"name": "Poor Crowbar",
			"description": "<p>Useful as both a tool and a weapon. A rod of iron with split wedges on the ends.  If you roll 1 on Attack (Crit Fail) the weapon fails in some way and requires an action to be made usable again.</p>"
		},
		"Poor Grenade Launcher": {
			"name": "Poor Grenade Launcher",
			"description": "<p>A high-impact grenade launcher. You can use a variety of grenades with this.  If you roll 1 on Attack (Crit fail) the gun jams and requires using an action to clear. </p>"
		},
		"Poor Heavy Pistol": {
			"name": "Poor Heavy Pistol",
			"description": "<p>A concealable, heavy pistol.  If you roll 1 on Attack (Crit fail) the gun jams and requires using an action to clear. </p>"
		},
		"Poor Heavy SMG": {
			"name": "Poor Heavy SMG",
			"description": "<p>A heavy SMG. Due to its size it can't be concealed.  If you roll 1 on Attack (Crit fail) the gun jams and requires using an action to clear. </p>"
		},
		"Poor Helicopter Blades": {
			"name": "Poor Helicopter Blades",
			"description": "<p>Taken from a derelict aircraft, these blades are capable of slicing most things easily.  If you roll 1 on Attack (Crit Fail) the weapon fails in some way and requires an action to be made usable again.</p>"
		},
		"Poor Lead Pipe": {
			"name": "Poor Lead Pipe",
			"description": "<p>A hollow cylinder, typically made of metal or fiberglass. It may have conveyed fluids once.  If you roll 1 on Attack (Crit Fail) the weapon fails in some way and requires an action to be made usable again.</p>"
		},
		"Poor Machete": {
			"name": "Poor Machete",
			"description": "<p>A long-bladed knife with a variety of uses. Known to be a favourite to some gangs  of Night City.  If you roll 1 on Attack (Crit Fail) the weapon fails in some way and requires an action to be made usable again.</p>"
		},
		"Poor Medium Pistol": {
			"name": "Poor Medium Pistol",
			"description": "<p>A concealable, medium-sized pistol. If you roll 1 on Attack (Crit fail) the gun jams and requires using an action to clear. </p>"
		},
		"Poor Naginata": {
			"name": "Poor Naginata",
			"description": "<p>A japanese wooden pole with a curved blade on one side. Favoured by Arasaka tactical teams for close engagements.  If you roll 1 on Attack (Crit Fail) the weapon fails in some way and requires an action to be made usable again.</p>"
		},
		"Poor Rocket Launcher": {
			"name": "Poor Rocket Launcher",
			"description": "<p>Bring out the big guns. This rocket launcher will do some damage.  If you roll 1 on Attack (Crit fail) the gun jams and requires using an action to clear. </p>"
		},
		"Poor SMG": {
			"name": "Poor SMG",
			"description": "<p>A concealable SMG.  If you roll 1 on Attack (Crit fail) the gun jams and requires using an action to clear. </p>"
		},
		"Poor Shotgun": {
			"name": "Poor Shotgun",
			"description": "<p>An all-purpose shotgun.  If you roll 1 on Attack (Crit fail) the gun jams and requires using an action to clear. </p>"
		},
		"Poor Sledgehammer": {
			"name": "Poor Sledgehammer",
			"description": "<p>A large mallet-like object with a flat metal head which distributes impacted force over a wide area.  If you roll 1 on Attack (Crit Fail) the weapon fails in some way and requires an action to be made usable again.</p>"
		},
		"Poor Sniper Rifle": {
			"name": "Poor Sniper Rifle",
			"description": "<p>A long-distance sniper rifle. Holds 4 bullets in a magazine.  If you roll 1 on Attack (Crit fail) the gun jams and requires using an action to clear. </p>"
		},
		"Poor Spiked Bat": {
			"name": "Poor Spiked Bat",
			"description": "<p>An advancement over a regular bat. A number of nails have been hammered through towards the tip.  If you roll 1 on Attack (Crit Fail) the weapon fails in some way and requires an action to be made usable again.</p>"
		},
		"Poor Sword": {
			"name": "Poor Sword",
			"description": "<p>A bladed, hilted weapon. Specifically designed for cutting or thrusting.  If you roll 1 on Attack (Crit Fail) the weapon fails in some way and requires an action to be made usable again.</p>"
		},
		"Poor Tomahawk": {
			"name": "Poor Tomahawk",
			"description": "<p>A light axe that can be thrown.  If you roll 1 on Attack (Crit Fail) the weapon fails in some way and requires an action to be made usable again.</p>"
		},
		"Poor Very Heavy Pistol": {
			"name": "Poor Very Heavy Pistol",
			"description": "<p>A very heavy pistol. It can't be concealed.  If you roll 1 on Attack (Crit fail) the gun jams and requires using an action to clear. </p>"
		},
		"Rippers": {
			"name": "Rippers",
			"description": "<p>Cyberware weapon. You must have the appropriate cyberware installed. </p>"
		},
		"Rocket Launcher": {
			"name": "Rocket Launcher",
			"description": "<p>Bring out the big guns. This rocket launcher will do some damage. </p>"
		},
		"SMG": {
			"name": "SMG",
			"description": "<p>A concealable SMG. </p>"
		},
		"Shotgun": {
			"name": "Shotgun",
			"description": "<p>An all-purpose shotgun. </p>"
		},
		"Sledgehammer": {
			"name": "Sledgehammer",
			"description": "<p>A large mallet-like object with a flat metal head which distributes impacted force over a wide area. </p>"
		},
		"Slice N' Dice": {
			"name": "Slice N' Dice",
			"description": "<p>Cyberware weapon. You must have the appropriate cyberware installed. </p>"
		},
		"Sniper Rifle": {
			"name": "Sniper Rifle",
			"description": "<p>A long-distance sniper rifle. Holds 4 bullets in a magazine. </p>"
		},
		"Spiked Bat": {
			"name": "Spiked Bat",
			"description": "<p>An advancement over a regular bat. A number of nails have been hammered through towards the tip. </p>"
		},
		"Sword": {
			"name": "Sword",
			"description": "<p>A bladed, hilted weapon. Specifically designed for cutting or thrusting. </p>"
		},
		"Talon Foot": {
			"name": "Talon Foot",
			"description": "<p>Cyberware weapon. You must have the appropriate cyberware installed. </p>"
		},
		"Tomahawk": {
			"name": "Tomahawk",
			"description": "<p>A light axe that can be thrown. </p>"
		},
		"Unarmed": {
			"name": "Unarmed",
			"description": "<p>Throwing hands, does not ignore half armor.</p>"
		},
		"Vampyres": {
			"name": "Vampyres",
			"description": "<p>Cyberware weapon. You must have the appropriate cyberware installed. </p>"
		},
		"Very Heavy Pistol": {
			"name": "Very Heavy Pistol",
			"description": "<p>A very heavy pistol. It can't be concealed. </p>"
		},
		"Wolvers": {
			"name": "Wolvers",
			"description": "<p>Cyberware weapon. You must have the appropriate cyberware installed. </p>"
		}
	}
}